opteryx/__init__.py
opteryx/__main__.py
opteryx/__version__.py
opteryx/command.py
opteryx/compute.cpython-312-darwin.so
opteryx/config.py
opteryx/connection.py
opteryx/cursor.py
opteryx/debugging.py
opteryx/exceptions.py
opteryx/compiled/__init__.py
opteryx/compiled/simd_probe.cpp
opteryx/compiled/simd_probe.cpython-312-darwin.so
opteryx/compiled/simd_probe.pyx
opteryx/compiled/aggregations/__init__.py
opteryx/compiled/aggregations/count_distinct.cpp
opteryx/compiled/aggregations/count_distinct.cpython-312-darwin.so
opteryx/compiled/aggregations/count_distinct.pyi
opteryx/compiled/aggregations/count_distinct.pyx
opteryx/compiled/aggregations/group_by_draken.py
opteryx/compiled/aggregations/group_by_draken.pyx
opteryx/compiled/functions/__init__.py
opteryx/compiled/functions/strings.cpp
opteryx/compiled/functions/strings.cpython-312-darwin.so
opteryx/compiled/functions/strings.pyx
opteryx/compiled/functions/timestamp.c
opteryx/compiled/functions/timestamp.cpython-312-darwin.so
opteryx/compiled/functions/timestamp.pyx
opteryx/compiled/functions/vectors.cpp
opteryx/compiled/functions/vectors.cpython-312-darwin.so
opteryx/compiled/functions/vectors.pyx
opteryx/compiled/io/__init__.py
opteryx/compiled/io/disk_reader.cpp
opteryx/compiled/io/disk_reader.cpython-312-darwin.so
opteryx/compiled/io/disk_reader.pyx
opteryx/compiled/joins/__init__.py
opteryx/compiled/joins/cross_join.pyx
opteryx/compiled/joins/filter_join.pyx
opteryx/compiled/joins/inner_join.pyx
opteryx/compiled/joins/join_definitions.cpython-312-darwin.so
opteryx/compiled/joins/joins.cpp
opteryx/compiled/joins/joins.pyx
opteryx/compiled/joins/nested_loop_join_equals.pyx
opteryx/compiled/joins/nested_loop_join_non_eqi.pyx
opteryx/compiled/joins/outer_join.pyx
opteryx/compiled/list_ops/__init__.py
opteryx/compiled/list_ops/function_definitions.cpython-312-darwin.so
opteryx/compiled/list_ops/list_allop_eq.pyx
opteryx/compiled/list_ops/list_allop_neq.pyx
opteryx/compiled/list_ops/list_anyop_eq.pyx
opteryx-0.26.7.dist-info/licenses/LICENSE
opteryx-0.26.7.dist-info/METADATA
opteryx-0.26.7.dist-info/WHEEL
opteryx-0.26.7.dist-info/entry_points.txt
opteryx-0.26.7.dist-info/top_level.txt
opteryx-0.26.7.dist-info/RECORD
