Metadata-Version: 2.4
Name: opteryx
Version: 0.26.7
Summary: Query your data, where it lives
Home-page: https://github.com/mabel-dev/opteryx/
Author-email: Justin Joyce <justin.joyce@joocer.com>
Maintainer-email: Justin Joyce <justin.joyce@joocer.com>
Project-URL: Homepage, https://opteryx.dev/
Project-URL: Documentation, https://opteryx.dev/
Project-URL: Repository, https://github.com/mabel-dev/opteryx.git
Requires-Python: >=3.11
License-File: LICENSE
Requires-Dist: aiohttp
Requires-Dist: numpy>=2.0.0
Requires-Dist: orjson
Requires-Dist: orso>=0.0.204
Requires-Dist: psutil
Requires-Dist: pyarrow>=20.0.0
Requires-Dist: requests
Dynamic: home-page
Dynamic: license-file
Dynamic: requires-python
